footprints/__init__.py
footprints/agent.py
footprints/ticket.py
footprints/timeline.py
footprints/util.py
TTFootprints-0.0.5.dist-info/METADATA
TTFootprints-0.0.5.dist-info/WHEEL
TTFootprints-0.0.5.dist-info/top_level.txt
TTFootprints-0.0.5.dist-info/RECORD
