Metadata-Version: 2.1
Name: TTFootprints
Version: 0.0.5
Summary: A library for working with exported data from BMC Footprints 11.
Home-page: https://gitlab.uvm.edu/whunt1/libfp
Author: Willem Hunt
Author-email: Willem.Hunt@uvm.edu
License: UNKNOWN
Platform: UNKNOWN
Requires-Python: >=3.6
